pydynu/__init__.py
pydynu/pydynu.py
pydynu/utils.py
pydynu-0.1.0.dist-info/LICENSE
pydynu-0.1.0.dist-info/METADATA
pydynu-0.1.0.dist-info/WHEEL
pydynu-0.1.0.dist-info/top_level.txt
pydynu-0.1.0.dist-info/RECORD
