Metadata-Version: 2.1
Name: pydynu
Version: 0.1.0
Summary: An API wrapper for Dynu ddns.
Home-page: https://github.com/Imperator26/pydynu
Author: Federico A. Corazza
Author-email: federico.corazza@love.it
License: UNKNOWN
Platform: UNKNOWN
Classifier: Programming Language :: Python :: 3
Classifier: License :: OSI Approved :: GNU General Public License v3 (GPLv3)
Classifier: Operating System :: OS Independent
Requires-Dist: requests
